django_expression_index/__init__.py
django_expression_index/index.py
django_expression_index-0.2.1.dist-info/LICENSE
django_expression_index-0.2.1.dist-info/METADATA
django_expression_index-0.2.1.dist-info/WHEEL
django_expression_index-0.2.1.dist-info/top_level.txt
django_expression_index-0.2.1.dist-info/RECORD
