Metadata-Version: 2.1
Name: django-expression-index
Version: 0.2.1
Summary: Subclass of django.db.models.Index, which enables indexing on expressions.
Home-page: https://github.com/kmierzeje/django-expression-index
Author: Kamil Mierzejewski
License: UNKNOWN
Platform: UNKNOWN
Classifier: Development Status :: 4 - Beta
Classifier: Environment :: Web Environment
Classifier: Framework :: Django
Classifier: Intended Audience :: Developers
Classifier: License :: OSI Approved :: BSD License
Classifier: Natural Language :: English
Classifier: Operating System :: OS Independent
Classifier: Programming Language :: Python :: 3.7
Requires-Dist: django (>=2.2.13)
